pydoris/__init__.py
pydoris/doris_client.py
pydoris/sqlalchemy/__init__.py
pydoris/sqlalchemy/datatype.py
pydoris/sqlalchemy/dialect.py
pydoris-1.1.0.dist-info/licenses/LICENSE
pydoris-1.1.0.dist-info/METADATA
pydoris-1.1.0.dist-info/WHEEL
pydoris-1.1.0.dist-info/entry_points.txt
pydoris-1.1.0.dist-info/top_level.txt
pydoris-1.1.0.dist-info/RECORD
