Metadata-Version: 2.4
Name: pydoris
Version: 1.1.0
Summary: Python interface to Doris
Author: liujiwen-up, bingquanzhao, catpineapple
Maintainer-email: catpineapple <catpineapple1122@gmail.com>
License: Apache 2.0
Project-URL: Homepage, https://github.com/apache/doris
Project-URL: Repository, https://github.com/apache/doris
Classifier: Development Status :: 5 - Production/Stable
Classifier: Environment :: Console
Classifier: Intended Audience :: Developers
Classifier: License :: OSI Approved :: Apache Software License
Classifier: Programming Language :: Python
Classifier: Programming Language :: Python :: 3
Classifier: Programming Language :: Python :: Implementation :: CPython
Classifier: Programming Language :: Python :: Implementation :: PyPy
Classifier: Topic :: Database :: Front-Ends
Requires-Python: >=3.7
License-File: LICENSE
Requires-Dist: sqlalchemy<2,>=1.4
Requires-Dist: sqlalchemy-utils<0.39,>=0.38.3
Requires-Dist: mysqlclient<3,>=2.1.0
Requires-Dist: requests
Dynamic: license-file
